[{"category": "", "app": "Chrome", "id": "1", "context": "Google https://www.google.com.tw", "time": "2017/07/07 17:25:12", "event": "TYPE_VIEW_SCROLLED"}, {"category": "", "app": "Chrome", "id": "2", "context": "台北旅遊 - Google 搜尋 https://www.google.com.tw/search?site=&source=hp&ei=ZFNfWf-_Jcq_0gSOva-IDw&q=台北旅遊&oq=台北旅遊&gs_l=mobile-gws-hp.3..0l5.7848.14598.0.15309.12.10.1.1.1.0.1783.3560.3j4j1j6-1j0j1.10.0....0...1.1j4.64.mobile-gws-hp..0.7.3168.3..41.NkaOxgbZmdU", "time": "2017/07/07 17:25:20", "event": "TYPE_VIEW_SCROLLED"}, {"category": "", "app": "Chrome", "id": "3", "context": "台北旅遊 - Google 搜尋 https://www.google.com.tw", "time": "2017/07/07 17:25:29", "event": "TYPE_VIEW_SCROLLED"}, {"category": "", "app": "Chrome", "id": "4", "context": "｜台北旅遊指南｜2017必去台北景點、美食及台北住宿攻略｜AsiaYo - AsiaYo.com ", "time": "2017/07/07 17:25:32", "event": "TYPE_VIEW_FOCUSED"}, {"category": "", "app": "Chrome", "id": "5", "context": "｜台北旅遊指南｜2017必去台北景點、美食及台北住宿攻略｜AsiaYo - AsiaYo.com  ", "time": "2017/07/07 17:25:34", "event": "TYPE_VIEW_CLICKED"}, {"category": "", "app": "Chrome", "id": "6", "context": "http://viablog.okmall.tw/mobile/blogview.php?blogid=323 ", "time": "2017/07/07 17:25:53", "event": "TYPE_VIEW_FOCUSED"}, {"category": "", "app": "Chrome", "id": "7", "context": "台北ㄕˋ  ", "time": "2017/07/07 17:26:06", "event": "TYPE_VIEW_TEXT_CHANGED"}, {"category": "", "app": "Chrome", "id": "8", "context": "台北市  ", "time": "2017/07/07 17:26:07", "event": "TYPE_VIEW_TEXT_CHANGED"}, {"category": "", "app": "Chrome", "id": "9", "context": "【台北市立動物園】台北木柵動物園貓熊～團團圓圓熊貓一日遊-Via's旅行札記 行動版 viablog.okmall.tw/mobile/blogview.php?blogid=323", "time": "2017/07/07 17:26:18", "event": "TYPE_VIEW_SCROLLED"}, {"category": "", "app": "Chrome", "id": "10", "context": "【台北市立動物園】台北木柵動物園貓熊～團團圓圓熊貓一日遊-Via's旅行札記 行動版 viablog.okmall.tw", "time": "2017/07/07 17:26:34", "event": "TYPE_VIEW_SCROLLED"}, {"category": "", "app": "Chrome", "id": "11", "context": "http://viablog.okmall.tw/mobile/blogview.php?blogid=323 ", "time": "2017/07/07 17:26:39", "event": "TYPE_VIEW_FOCUSED"}, {"category": "", "app": "Chrome", "id": "12", "context": "ㄌ  ", "time": "2017/07/07 17:26:47", "event": "TYPE_VIEW_TEXT_CHANGED"}, {"category": "", "app": "Chrome", "id": "13", "context": "搜尋或輸入網址  ", "time": "2017/07/07 17:26:48", "event": "TYPE_VIEW_TEXT_CHANGED"}, {"category": "", "app": "Chrome", "id": "14", "context": "ㄖ  ", "time": "2017/07/07 17:26:49", "event": "TYPE_VIEW_TEXT_CHANGED"}, {"category": "", "app": "Chrome", "id": "15", "context": "ㄖㄠ  ", "time": "2017/07/07 17:26:49", "event": "TYPE_VIEW_TEXT_CHANGED"}, {"category": "", "app": "Chrome", "id": "16", "context": "饒  ", "time": "2017/07/07 17:26:50", "event": "TYPE_VIEW_TEXT_CHANGED"}, {"category": "", "app": "Chrome", "id": "17", "context": "饒河  ", "time": "2017/07/07 17:26:51", "event": "TYPE_VIEW_TEXT_CHANGED"}, {"category": "", "app": "Chrome", "id": "18", "context": "饒河夜市 - Google 搜尋 https://www.google.com.tw/search?q=饒河夜市&oq=饒河&aqs=chrome.1.69i57j0l3.2918j0j4&client=ms-android-sonymobile&sourceid=chrome-mobile&ie=UTF-8", "time": "2017/07/07 17:26:55", "event": "TYPE_VIEW_SCROLLED"}, {"category": "", "app": "Chrome", "id": "19", "context": "【台北】松山饒河夜市美食攻略正常鮮肉小籠湯包、口袋吐司、爆漿芋、日式大阪燒 ... ", "time": "2017/07/07 17:27:04", "event": "TYPE_VIEW_FOCUSED"}, {"category": "", "app": "Chrome", "id": "20", "context": "饒河夜市 - Google 搜尋 https://www.google.com.tw", "time": "2017/07/07 17:27:04", "event": "TYPE_VIEW_SCROLLED"}, {"category": "", "app": "Chrome", "id": "21", "context": "【台北】松山饒河夜市美食攻略正常鮮肉小籠湯包、口袋吐司、爆漿芋、日式大阪燒 ...  ", "time": "2017/07/07 17:27:04", "event": "TYPE_VIEW_CLICKED"}, {"category": "", "app": "Chrome", "id": "22", "context": "饒河夜市 - Google 搜尋 https://www.google.com.tw", "time": "2017/07/07 17:27:05", "event": "TYPE_VIEW_SCROLLED"}, {"category": "", "app": "Chrome", "id": "23", "context": "饒河夜市 - Google 搜尋 vilo92.pixnet.net/blog/post/400064374-【台北】松山-饒河夜市美食攻略-正常鮮肉小", "time": "2017/07/07 17:27:06", "event": "TYPE_VIEW_SCROLLED"}, {"category": "", "app": "Chrome", "id": "24", "context": "【台北】松山 饒河夜市美食攻略 正常鮮肉小籠湯包、口袋吐司、爆漿芋、日式大阪燒、甘泉豆花‧人氣必吃推薦♥♥♥ @ YOYO♥♥♥愛生活 :: 痞客邦 PIXNET :: vilo92.pixnet.net", "time": "2017/07/07 17:27:21", "event": "TYPE_VIEW_SCROLLED"}, {"category": "", "app": "Chrome", "id": "25", "context": "饒河夜市 - Google 搜尋 https://www.google.com.tw/search?q=饒河夜市&oq=饒河&aqs=chrome.1.69i57j0l3.2918j0j4&client=ms-android-sonymobile&sourceid=chrome-mobile&ie=UTF-8", "time": "2017/07/07 17:31:36", "event": "TYPE_VIEW_SCROLLED"}, {"category": "", "app": "Chrome", "id": "26", "context": "【台北松山】饒河夜市懶人包攻略‧邊走邊吃邊逛30家美味整理!福州世祖胡椒餅 ... ", "time": "2017/07/07 17:31:39", "event": "TYPE_VIEW_FOCUSED"}, {"category": "", "app": "Chrome", "id": "27", "context": "【台北松山】饒河夜市懶人包攻略‧邊走邊吃邊逛30家美味整理!福州世祖胡椒餅 ...  ", "time": "2017/07/07 17:31:39", "event": "TYPE_VIEW_CLICKED"}, {"category": "", "app": "Chrome", "id": "28", "context": "饒河夜市 - Google 搜尋 zineblog.com.tw", "time": "2017/07/07 17:31:42", "event": "TYPE_VIEW_SCROLLED"}, {"category": "", "app": "Chrome", "id": "29", "context": "http://zineblog.com.tw/blog/post/47029588-%E3%80%90%E5%8F%B0%E5%8C%97%E6%9D%BE%E5%B1%B1%E3%80%91%E9%A5%92%E6%B2%B3%E5%A4%9C%E5%B8%82%E6%87%B6%E4%BA%BA%E5%8C%85%E6%94%BB%E7%95%A5%E2%80%A7%E9%82%8A%E8%B5%B0%E9%82%8A%E5%90%83 ", "time": "2017/07/07 17:31:43", "event": "TYPE_VIEW_FOCUSED"}, {"category": "", "app": "Chrome", "id": "30", "context": "ㄕ  ", "time": "2017/07/07 17:31:59", "event": "TYPE_VIEW_TEXT_CHANGED"}, {"category": "", "app": "Chrome", "id": "31", "context": "ㄕㄌ  ", "time": "2017/07/07 17:31:59", "event": "TYPE_VIEW_TEXT_CHANGED"}, {"category": "", "app": "Chrome", "id": "32", "context": "ㄕㄌㄧ  ", "time": "2017/07/07 17:32:00", "event": "TYPE_VIEW_TEXT_CHANGED"}, {"category": "", "app": "Chrome", "id": "33", "context": "ㄕㄌㄧㄣ  ", "time": "2017/07/07 17:32:00", "event": "TYPE_VIEW_TEXT_CHANGED"}, {"category": "", "app": "Chrome", "id": "34", "context": "士林  ", "time": "2017/07/07 17:32:01", "event": "TYPE_VIEW_TEXT_CHANGED"}, {"category": "", "app": "Chrome", "id": "35", "context": "【士林夜市必吃美食地圖攻略。台北士林】精選14家非吃不可懶人包！ - Livia's Wonderland薇笑樂園 ", "time": "2017/07/07 17:32:11", "event": "TYPE_VIEW_FOCUSED"}, {"category": "", "app": "Chrome", "id": "36", "context": "【士林夜市必吃美食地圖攻略。台北士林】精選14家非吃不可懶人包！ - Livia's Wonderland薇笑樂園  ", "time": "2017/07/07 17:32:11", "event": "TYPE_VIEW_CLICKED"}, {"category": "", "app": "Chrome", "id": "37", "context": "士林夜市 - Google 搜尋 https://www.google.com.tw", "time": "2017/07/07 17:32:11", "event": "TYPE_VIEW_SCROLLED"}, {"category": "", "app": "Chrome", "id": "38", "context": "士林夜市 - Google 搜尋 www.liviatravel.com/2015/10/shilin-night-market-must-eat.html?m=1", "time": "2017/07/07 17:32:13", "event": "TYPE_VIEW_SCROLLED"}, {"category": "", "app": "Chrome", "id": "39", "context": "【士林夜市必吃美食地圖攻略。台北士林】精選14家非吃不可懶人包！ - Livia's Wonderland薇笑樂園 www.liviatravel.com", "time": "2017/07/07 17:32:54", "event": "TYPE_VIEW_SCROLLED"}, {"category": "", "app": "Chrome", "id": "40", "context": "士林夜市 - Google 搜尋 https://www.google.com.tw/search?q=士林夜市&oq=士林&aqs=chrome.1.69i57j0l3.3958j0j4&client=ms-android-sonymobile&sourceid=chrome-mobile&ie=UTF-8", "time": "2017/07/07 17:34:08", "event": "TYPE_VIEW_SCROLLED"}, {"category": "", "app": "Chrome", "id": "41", "context": "https://www.google.com.tw/search?q=%E5%A3%AB%E6%9E%97%E5%A4%9C%E5%B8%82&oq=%E5%A3%AB%E6%9E%97&aqs=chrome.1.69i57j0l3.3958j0j4&client=ms-android-sonymobile&sourceid=chrome-mobile&ie=UTF-8 ", "time": "2017/07/07 17:34:10", "event": "TYPE_VIEW_FOCUSED"}, {"category": "", "app": "Chrome", "id": "42", "context": "ㄙ  ", "time": "2017/07/07 17:34:15", "event": "TYPE_VIEW_TEXT_CHANGED"}, {"category": "", "app": "Chrome", "id": "43", "context": "ㄙㄨㄥ  ", "time": "2017/07/07 17:34:15", "event": "TYPE_VIEW_TEXT_CHANGED"}, {"category": "", "app": "Chrome", "id": "44", "context": "松  ", "time": "2017/07/07 17:34:16", "event": "TYPE_VIEW_TEXT_CHANGED"}, {"category": "", "app": "Chrome", "id": "45", "context": "松煙  ", "time": "2017/07/07 17:34:17", "event": "TYPE_VIEW_TEXT_CHANGED"}, {"category": "", "app": "Chrome", "id": "46", "context": "松煙 - Google 搜尋 https://www.google.com.tw/search?q=松煙&oq=松煙&aqs=chrome..69i57j0l3.3225j0j4&client=ms-android-sonymobile&sourceid=chrome-mobile&ie=UTF-8", "time": "2017/07/07 17:34:19", "event": "TYPE_VIEW_SCROLLED"}, {"category": "", "app": "Chrome", "id": "47", "context": "松山文創園區 ", "time": "2017/07/07 17:34:26", "event": "TYPE_VIEW_FOCUSED"}, {"category": "", "app": "Chrome", "id": "48", "context": "松山文創園區 www.songshanculturalpark.org/m/Index.aspx", "time": "2017/07/07 17:34:26", "event": "TYPE_VIEW_SCROLLED"}, {"category": "", "app": "Chrome", "id": "49", "context": "http://www.songshanculturalpark.org/m/Index.aspx ", "time": "2017/07/07 17:34:57", "event": "TYPE_VIEW_FOCUSED"}, {"category": "", "app": "Chrome", "id": "50", "context": "搜尋或輸入網址  ", "time": "2017/07/07 17:34:58", "event": "TYPE_VIEW_TEXT_CHANGED"}, {"category": "", "app": "Chrome", "id": "51", "context": "http://www.songshanculturalpark.org/m/Index.aspx ", "time": "2017/07/07 17:36:37", "event": "TYPE_VIEW_FOCUSED"}, {"category": "", "app": "Chrome", "id": "52", "context": "ㄏ  ", "time": "2017/07/07 17:36:49", "event": "TYPE_VIEW_TEXT_CHANGED"}, {"category": "", "app": "Chrome", "id": "53", "context": "ㄏㄨ  ", "time": "2017/07/07 17:36:49", "event": "TYPE_VIEW_TEXT_CHANGED"}, {"category": "", "app": "Chrome", "id": "54", "context": "ㄏㄨㄚㄕ  ", "time": "2017/07/07 17:36:49", "event": "TYPE_VIEW_TEXT_CHANGED"}, {"category": "", "app": "Chrome", "id": "55", "context": "ㄏㄨㄚㄕㄢ  ", "time": "2017/07/07 17:36:50", "event": "TYPE_VIEW_TEXT_CHANGED"}, {"category": "", "app": "Chrome", "id": "56", "context": "華山  ", "time": "2017/07/07 17:36:50", "event": "TYPE_VIEW_TEXT_CHANGED"}, {"category": "", "app": "Chrome", "id": "57", "context": "華山 - Google 搜尋 https://www.google.com.tw/search?q=華山&oq=華山&aqs=chrome..69i57j0j5j0.1378j0j4&client=ms-android-sonymobile&sourceid=chrome-mobile&ie=UTF-8", "time": "2017/07/07 17:36:53", "event": "TYPE_VIEW_SCROLLED"}, {"category": "", "app": "Chrome", "id": "58", "context": "顯示星期五熱門時段的直方圖 ", "time": "2017/07/07 17:36:56", "event": "TYPE_VIEW_FOCUSED"}, {"category": "", "app": "Chrome", "id": "59", "context": "表演與展覽 - 華山1914文化創意產業園區 ", "time": "2017/07/07 17:36:59", "event": "TYPE_VIEW_FOCUSED"}, {"category": "", "app": "Chrome", "id": "60", "context": "表演與展覽 - 華山1914文化創意產業園區  ", "time": "2017/07/07 17:37:00", "event": "TYPE_VIEW_CLICKED"}, {"category": "", "app": "Chrome", "id": "61", "context": ":: 華山1914文化創意產業園區 :: www.huashan1914.com/exhibition/playing.php", "time": "2017/07/07 17:37:00", "event": "TYPE_VIEW_SCROLLED"}, {"category": "", "app": "Chrome", "id": "62", "context": "搜尋或輸入網址 ", "time": "2017/07/07 17:37:05", "event": "TYPE_VIEW_FOCUSED"}, {"category": "", "app": "Chrome", "id": "63", "context": "搜尋或輸入網址  ", "time": "2017/07/07 17:37:05", "event": "TYPE_VIEW_TEXT_CHANGED"}, {"category": "", "app": "Chrome", "id": "64", "context": "ㄒ  ", "time": "2017/07/07 17:37:06", "event": "TYPE_VIEW_TEXT_CHANGED"}, {"category": "", "app": "Chrome", "id": "65", "context": "ㄒㄧ  ", "time": "2017/07/07 17:37:09", "event": "TYPE_VIEW_TEXT_CHANGED"}, {"category": "", "app": "Chrome", "id": "66", "context": "ㄒㄧㄇ  ", "time": "2017/07/07 17:37:10", "event": "TYPE_VIEW_TEXT_CHANGED"}, {"category": "", "app": "Chrome", "id": "67", "context": "ㄒㄧㄇㄣ  ", "time": "2017/07/07 17:37:10", "event": "TYPE_VIEW_TEXT_CHANGED"}, {"category": "", "app": "Chrome", "id": "68", "context": "西門  ", "time": "2017/07/07 17:37:10", "event": "TYPE_VIEW_TEXT_CHANGED"}, {"category": "", "app": "Chrome", "id": "69", "context": "西門町  ", "time": "2017/07/07 17:37:11", "event": "TYPE_VIEW_TEXT_CHANGED"}, {"category": "", "app": "Chrome", "id": "70", "context": "西門町 - Google 搜尋 https://www.google.com.tw/search?q=西門町&oq=西門町&aqs=chrome..69i57j0l3.4790j0j4&client=ms-android-sonymobile&sourceid=chrome-mobile&ie=UTF-8", "time": "2017/07/07 17:37:12", "event": "TYPE_VIEW_SCROLLED"}, {"category": "", "app": "Chrome", "id": "71", "context": "【揪是要食西門町】在地人推薦！西門町必吃TOP 10必吃美食+甜點 - 啾啾瘋旅行 - 痞客邦PIXNET ", "time": "2017/07/07 17:37:15", "event": "TYPE_VIEW_FOCUSED"}, {"category": "", "app": "Chrome", "id": "72", "context": "【揪是要食西門町】在地人推薦！西門町必吃TOP 10必吃美食+甜點 - 啾啾瘋旅行 - 痞客邦PIXNET  ", "time": "2017/07/07 17:37:15", "event": "TYPE_VIEW_CLICKED"}, {"category": "", "app": "Chrome", "id": "73", "context": "【揪是要食西門町】在地人推薦！西門町必吃TOP 10必吃美食+甜點 @ 啾啾の旅行紀錄 :: 痞客邦 PIXNET :: chu94168.pixnet.net", "time": "2017/07/07 17:37:18", "event": "TYPE_VIEW_SCROLLED"}, {"category": "", "app": "Chrome", "id": "74", "context": "http://chu94168.pixnet.net/blog/post/111503102-%E8%A5%BF%E9%96%80%E7%94%BA%E5%BF%85%E5%90%83 ", "time": "2017/07/07 17:37:22", "event": "TYPE_VIEW_FOCUSED"}, {"category": "", "app": "Chrome", "id": "75", "context": "搜尋或輸入網址  ", "time": "2017/07/07 17:37:22", "event": "TYPE_VIEW_TEXT_CHANGED"}, {"category": "", "app": "Chrome", "id": "76", "context": "ㄖ  ", "time": "2017/07/07 17:37:26", "event": "TYPE_VIEW_TEXT_CHANGED"}, {"category": "", "app": "Chrome", "id": "77", "context": "搜尋或輸入網址  ", "time": "2017/07/07 17:37:26", "event": "TYPE_VIEW_TEXT_CHANGED"}, {"category": "", "app": "Chrome", "id": "78", "context": "ㄙ  ", "time": "2017/07/07 17:37:26", "event": "TYPE_VIEW_TEXT_CHANGED"}, {"category": "", "app": "Chrome", "id": "79", "context": "ㄙㄙ  ", "time": "2017/07/07 17:37:26", "event": "TYPE_VIEW_TEXT_CHANGED"}, {"category": "", "app": "Chrome", "id": "80", "context": "搜尋或輸入網址  ", "time": "2017/07/07 17:37:27", "event": "TYPE_VIEW_TEXT_CHANGED"}, {"category": "", "app": "Chrome", "id": "81", "context": "ㄊ  ", "time": "2017/07/07 17:37:30", "event": "TYPE_VIEW_TEXT_CHANGED"}, {"category": "", "app": "Chrome", "id": "82", "context": "ㄊㄞㄅ  ", "time": "2017/07/07 17:37:30", "event": "TYPE_VIEW_TEXT_CHANGED"}, {"category": "", "app": "Chrome", "id": "83", "context": "台北  ", "time": "2017/07/07 17:37:30", "event": "TYPE_VIEW_TEXT_CHANGED"}, {"category": "", "app": "Chrome", "id": "84", "context": "台北ㄈ  ", "time": "2017/07/07 17:37:31", "event": "TYPE_VIEW_TEXT_CHANGED"}, {"category": "", "app": "Chrome", "id": "85", "context": "台北ㄈㄅ  ", "time": "2017/07/07 17:37:31", "event": "TYPE_VIEW_TEXT_CHANGED"}, {"category": "", "app": "Chrome", "id": "86", "context": "台北ㄈ  ", "time": "2017/07/07 17:37:33", "event": "TYPE_VIEW_TEXT_CHANGED"}, {"category": "", "app": "Chrome", "id": "87", "context": "台北  ", "time": "2017/07/07 17:37:33", "event": "TYPE_VIEW_TEXT_CHANGED"}, {"category": "", "app": "Chrome", "id": "88", "context": "台北ㄅ  ", "time": "2017/07/07 17:37:33", "event": "TYPE_VIEW_TEXT_CHANGED"}, {"category": "", "app": "Chrome", "id": "89", "context": "台北ㄅㄦ  ", "time": "2017/07/07 17:37:33", "event": "TYPE_VIEW_TEXT_CHANGED"}, {"category": "", "app": "Chrome", "id": "90", "context": "台北ㄅ  ", "time": "2017/07/07 17:37:34", "event": "TYPE_VIEW_TEXT_CHANGED"}, {"category": "", "app": "Chrome", "id": "91", "context": "台北  ", "time": "2017/07/07 17:37:34", "event": "TYPE_VIEW_TEXT_CHANGED"}, {"category": "", "app": "Chrome", "id": "92", "context": "台北1  ", "time": "2017/07/07 17:37:35", "event": "TYPE_VIEW_TEXT_CHANGED"}, {"category": "", "app": "Chrome", "id": "93", "context": "台北101  ", "time": "2017/07/07 17:37:35", "event": "TYPE_VIEW_TEXT_CHANGED"}, {"category": "", "app": "Chrome", "id": "94", "context": "台北101 - Google 搜尋 https://www.google.com.tw/search?q=台北101&oq=台北101&aqs=chrome..69i57j0j5j0.5950j0j4&client=ms-android-sonymobile&sourceid=chrome-mobile&ie=UTF-8", "time": "2017/07/07 17:37:38", "event": "TYPE_VIEW_SCROLLED"}, {"category": "", "app": "Chrome", "id": "95", "context": "台北101官方網站 ", "time": "2017/07/07 17:37:40", "event": "TYPE_VIEW_FOCUSED"}, {"category": "", "app": "Chrome", "id": "96", "context": "台北101官方網站  ", "time": "2017/07/07 17:37:40", "event": "TYPE_VIEW_CLICKED"}, {"category": "", "app": "Chrome", "id": "97", "context": "台北101 - Google 搜尋 www.taipei-101.com.tw", "time": "2017/07/07 17:37:42", "event": "TYPE_VIEW_SCROLLED"}, {"category": "", "app": "Chrome", "id": "98", "context": "101 Taipei Financial Center Corp. 台北101官方網站 www.taipei-101.com.tw", "time": "2017/07/07 17:37:42", "event": "TYPE_VIEW_SCROLLED"}, {"category": "", "app": "Chrome", "id": "99", "context": "http://www.taipei-101.com.tw/m/ ", "time": "2017/07/07 17:38:01", "event": "TYPE_VIEW_FOCUSED"}, {"category": "", "app": "Chrome", "id": "100", "context": "搜尋或輸入網址  ", "time": "2017/07/07 17:38:01", "event": "TYPE_VIEW_TEXT_CHANGED"}, {"category": "", "app": "Chrome", "id": "101", "context": "ㄉ  ", "time": "2017/07/07 17:38:17", "event": "TYPE_VIEW_TEXT_CHANGED"}, {"category": "", "app": "Chrome", "id": "102", "context": "ㄉㄨ  ", "time": "2017/07/07 17:38:18", "event": "TYPE_VIEW_TEXT_CHANGED"}, {"category": "", "app": "Chrome", "id": "103", "context": "ㄉㄨㄥ  ", "time": "2017/07/07 17:38:18", "event": "TYPE_VIEW_TEXT_CHANGED"}, {"category": "", "app": "Chrome", "id": "104", "context": "ㄉㄨㄥㄒ  ", "time": "2017/07/07 17:38:18", "event": "TYPE_VIEW_TEXT_CHANGED"}, {"category": "", "app": "Chrome", "id": "105", "context": "ㄉㄨㄥ  ", "time": "2017/07/07 17:38:18", "event": "TYPE_VIEW_TEXT_CHANGED"}, {"category": "", "app": "Chrome", "id": "106", "context": "ㄉㄨㄥㄑ  ", "time": "2017/07/07 17:38:19", "event": "TYPE_VIEW_TEXT_CHANGED"}, {"category": "", "app": "Chrome", "id": "107", "context": "東區  ", "time": "2017/07/07 17:38:19", "event": "TYPE_VIEW_TEXT_CHANGED"}, {"category": "", "app": "Chrome", "id": "108", "context": "東區 - Google 搜尋 https://www.google.com.tw/search?q=東區&oq=東區&aqs=chrome..69i57j0j5j0.1942j0j4&client=ms-android-sonymobile&sourceid=chrome-mobile&ie=UTF-8", "time": "2017/07/07 17:38:23", "event": "TYPE_VIEW_SCROLLED"}, {"category": "", "app": "Chrome", "id": "109", "context": "臺北東區- 维基百科，自由的百科全书 - 維基百科 ", "time": "2017/07/07 17:38:24", "event": "TYPE_VIEW_FOCUSED"}, {"category": "", "app": "Chrome", "id": "110", "context": "臺北東區- 维基百科，自由的百科全书 - 維基百科  ", "time": "2017/07/07 17:38:24", "event": "TYPE_VIEW_CLICKED"}, {"category": "", "app": "Chrome", "id": "111", "context": "東區 - Google 搜尋 https://www.google.com.tw/search?q=東區&oq=東區&aqs=chrome..69i57j0j5j0.1942j0j4&client=ms-android-sonymobile&sourceid=chrome-mobile&ie=UTF-8", "time": "2017/07/07 17:38:25", "event": "TYPE_VIEW_SCROLLED"}, {"category": "", "app": "Chrome", "id": "112", "context": "臺北東區 - 維基百科，自由的百科全書 https://zh.m.wikipedia.org/zh-tw/臺北東區", "time": "2017/07/07 17:38:28", "event": "TYPE_VIEW_SCROLLED"}, {"category": "", "app": "Chrome", "id": "113", "context": "https://zh.m.wikipedia.org/zh-tw/%E8%87%BA%E5%8C%97%E6%9D%B1%E5%8D%80 ", "time": "2017/07/07 17:38:29", "event": "TYPE_VIEW_FOCUSED"}, {"category": "", "app": "Chrome", "id": "114", "context": "搜尋或輸入網址  ", "time": "2017/07/07 17:38:29", "event": "TYPE_VIEW_TEXT_CHANGED"}, {"category": "", "app": "Chrome", "id": "115", "context": "ㄦ  ", "time": "2017/07/07 17:38:39", "event": "TYPE_VIEW_TEXT_CHANGED"}, {"category": "", "app": "Chrome", "id": "116", "context": "ㄦㄊ  ", "time": "2017/07/07 17:38:39", "event": "TYPE_VIEW_TEXT_CHANGED"}, {"category": "", "app": "Chrome", "id": "117", "context": "兒童  ", "time": "2017/07/07 17:38:40", "event": "TYPE_VIEW_TEXT_CHANGED"}, {"category": "", "app": "Chrome", "id": "118", "context": "兒童ㄒ  ", "time": "2017/07/07 17:38:40", "event": "TYPE_VIEW_TEXT_CHANGED"}, {"category": "", "app": "Chrome", "id": "119", "context": "兒童ㄒㄧ  ", "time": "2017/07/07 17:38:40", "event": "TYPE_VIEW_TEXT_CHANGED"}, {"category": "", "app": "Chrome", "id": "120", "context": "兒童ㄒㄧㄣ  ", "time": "2017/07/07 17:38:40", "event": "TYPE_VIEW_TEXT_CHANGED"}, {"category": "", "app": "Chrome", "id": "121", "context": "兒童新  ", "time": "2017/07/07 17:38:41", "event": "TYPE_VIEW_TEXT_CHANGED"}, {"category": "", "app": "Chrome", "id": "122", "context": "兒童新ㄌ  ", "time": "2017/07/07 17:38:41", "event": "TYPE_VIEW_TEXT_CHANGED"}, {"category": "", "app": "Chrome", "id": "123", "context": "兒童新ㄌㄜ  ", "time": "2017/07/07 17:38:42", "event": "TYPE_VIEW_TEXT_CHANGED"}, {"category": "", "app": "Chrome", "id": "124", "context": "兒童新ㄌㄜㄩ  ", "time": "2017/07/07 17:38:42", "event": "TYPE_VIEW_TEXT_CHANGED"}, {"category": "", "app": "Chrome", "id": "125", "context": "兒童新ㄌㄜㄩㄢ  ", "time": "2017/07/07 17:38:42", "event": "TYPE_VIEW_TEXT_CHANGED"}, {"category": "", "app": "Chrome", "id": "126", "context": "兒童新樂園  ", "time": "2017/07/07 17:38:42", "event": "TYPE_VIEW_TEXT_CHANGED"}, {"category": "", "app": "Chrome", "id": "127", "context": "兒童新樂園 - Google 搜尋 https://www.google.com.tw/search?q=兒童新樂園&oq=兒童新樂園&aqs=chrome..69i57j69i61j0l3.3771j0j4&client=ms-android-sonymobile&sourceid=chrome-mobile&ie=UTF-8", "time": "2017/07/07 17:38:44", "event": "TYPE_VIEW_SCROLLED"}, {"category": "", "app": "Chrome", "id": "128", "context": "遊樂設施 ", "time": "2017/07/07 17:38:48", "event": "TYPE_VIEW_FOCUSED"}, {"category": "", "app": "Chrome", "id": "129", "context": "遊樂設施  ", "time": "2017/07/07 17:38:48", "event": "TYPE_VIEW_CLICKED"}, {"category": "", "app": "Chrome", "id": "130", "context": "兒童新樂園 - Google 搜尋 https://www.google.com.tw", "time": "2017/07/07 17:38:48", "event": "TYPE_VIEW_SCROLLED"}, {"category": "", "app": "Chrome", "id": "131", "context": "兒童新樂園 ─ 遊園資訊 www.tcap.taipei/np.asp?ctNode=72246&mp=122037", "time": "2017/07/07 17:38:50", "event": "TYPE_VIEW_SCROLLED"}, {"category": "", "app": "Chrome", "id": "132", "context": "http://www.tcap.taipei/np.asp?ctNode=72246&mp=122037 ", "time": "2017/07/07 17:39:20", "event": "TYPE_VIEW_FOCUSED"}, {"category": "", "app": "Chrome", "id": "133", "context": "搜尋或輸入網址  ", "time": "2017/07/07 17:39:20", "event": "TYPE_VIEW_TEXT_CHANGED"}, {"category": "", "app": "Chrome", "id": "134", "context": "ㄉ  ", "time": "2017/07/07 17:39:26", "event": "TYPE_VIEW_TEXT_CHANGED"}, {"category": "", "app": "Chrome", "id": "135", "context": "ㄉㄢ  ", "time": "2017/07/07 17:39:27", "event": "TYPE_VIEW_TEXT_CHANGED"}, {"category": "", "app": "Chrome", "id": "136", "context": "淡  ", "time": "2017/07/07 17:39:28", "event": "TYPE_VIEW_TEXT_CHANGED"}, {"category": "", "app": "Chrome", "id": "137", "context": "淡水  ", "time": "2017/07/07 17:39:28", "event": "TYPE_VIEW_TEXT_CHANGED"}, {"category": "", "app": "Chrome", "id": "138", "context": "[懶人包] 淡水旅遊：古蹟、景點與美食完全攻略(2017) 1394 @ 貓大爺部落格:: 隨意窩Xuite日誌 ", "time": "2017/07/07 17:39:35", "event": "TYPE_VIEW_FOCUSED"}, {"category": "", "app": "Chrome", "id": "139", "context": "[懶人包] 淡水旅遊：古蹟、景點與美食完全攻略(2017) 1394 @ 貓大爺部落格:: 隨意窩Xuite日誌  ", "time": "2017/07/07 17:39:35", "event": "TYPE_VIEW_CLICKED"}, {"category": "", "app": "Chrome", "id": "140", "context": "淡水 - Google 搜尋 https://www.google.com.tw", "time": "2017/07/07 17:39:36", "event": "TYPE_VIEW_SCROLLED"}, {"category": "", "app": "Chrome", "id": "141", "context": "[懶人包] 淡水旅遊：古蹟、景點與美食完全攻略 (2017) 1394 @ 貓大爺部落格 :: 隨意窩 Xuite日誌 m.xuite.net/blog/maomi/Food01/66213224", "time": "2017/07/07 17:39:38", "event": "TYPE_VIEW_SCROLLED"}, {"category": "", "app": "Chrome", "id": "142", "context": "[懶人包] 淡水旅遊：古蹟、景點與美食完全攻略 (2017) 1394 @ 貓大爺部落格 :: 隨意窩 Xuite日誌 m.xuite.net", "time": "2017/07/07 17:39:43", "event": "TYPE_VIEW_SCROLLED"}, {"category": "", "app": "Chrome", "id": "143", "context": "紅毛城 ", "time": "2017/07/07 17:39:54", "event": "TYPE_VIEW_FOCUSED"}, {"category": "", "app": "Chrome", "id": "144", "context": "紅毛城  ", "time": "2017/07/07 17:39:54", "event": "TYPE_VIEW_CLICKED"}, {"category": "", "app": "Chrome", "id": "145", "context": "[淡水旅遊] 淡水紅毛城：殖民時代的紅色歐風城堡 (國定古蹟) 1196 @ 貓大爺部落格 :: 隨意窩 Xuite日誌 blog.xuite.net", "time": "2017/07/07 17:40:17", "event": "TYPE_VIEW_SCROLLED"}, {"category": "", "app": "Chrome", "id": "146", "context": "搜尋或輸入網址 ", "time": "2017/07/07 17:40:22", "event": "TYPE_VIEW_FOCUSED"}, {"category": "", "app": "Chrome", "id": "147", "context": "搜尋或輸入網址  ", "time": "2017/07/07 17:40:22", "event": "TYPE_VIEW_TEXT_CHANGED"}, {"category": "", "app": "Chrome", "id": "148", "context": "ㄇ  ", "time": "2017/07/07 17:40:25", "event": "TYPE_VIEW_TEXT_CHANGED"}, {"category": "", "app": "Chrome", "id": "149", "context": "搜尋或輸入網址  ", "time": "2017/07/07 17:40:25", "event": "TYPE_VIEW_TEXT_CHANGED"}, {"category": "", "app": "Chrome", "id": "150", "context": "ㄊ  ", "time": "2017/07/07 17:40:48", "event": "TYPE_VIEW_TEXT_CHANGED"}, {"category": "", "app": "Chrome", "id": "151", "context": "ㄊㄞ  ", "time": "2017/07/07 17:40:48", "event": "TYPE_VIEW_TEXT_CHANGED"}, {"category": "", "app": "Chrome", "id": "152", "context": "ㄊㄞㄅ  ", "time": "2017/07/07 17:40:48", "event": "TYPE_VIEW_TEXT_CHANGED"}, {"category": "", "app": "Chrome", "id": "153", "context": "台北  ", "time": "2017/07/07 17:40:49", "event": "TYPE_VIEW_TEXT_CHANGED"}, {"category": "", "app": "Chrome", "id": "154", "context": "台北ㄔ  ", "time": "2017/07/07 17:40:50", "event": "TYPE_VIEW_TEXT_CHANGED"}, {"category": "", "app": "Chrome", "id": "155", "context": "台北ㄔㄜ  ", "time": "2017/07/07 17:40:50", "event": "TYPE_VIEW_TEXT_CHANGED"}, {"category": "", "app": "Chrome", "id": "156", "context": "台北ㄔㄜㄓ  ", "time": "2017/07/07 17:40:50", "event": "TYPE_VIEW_TEXT_CHANGED"}, {"category": "", "app": "Chrome", "id": "157", "context": "台北車站  ", "time": "2017/07/07 17:40:50", "event": "TYPE_VIEW_TEXT_CHANGED"}, {"category": "", "app": "Chrome", "id": "158", "context": "台北車站 - 臺灣鐵路管理局 ", "time": "2017/07/07 17:41:20", "event": "TYPE_VIEW_FOCUSED"}, {"category": "", "app": "Chrome", "id": "159", "context": "台北車站 - 臺灣鐵路管理局  ", "time": "2017/07/07 17:41:20", "event": "TYPE_VIEW_CLICKED"}, {"category": "", "app": "Chrome", "id": "160", "context": "歡迎光臨交通部台灣鐵路管理局 www.railway.gov.tw/taipei/", "time": "2017/07/07 17:41:21", "event": "TYPE_VIEW_SCROLLED"}, {"category": "", "app": "Chrome", "id": "161", "context": "台北車站 www.railway.gov.tw", "time": "2017/07/07 17:41:27", "event": "TYPE_VIEW_SCROLLED"}, {"category": "", "app": "Chrome", "id": "162", "context": "臺北站介紹   》 臺北站介紹 ", "time": "2017/07/07 17:41:32", "event": "TYPE_VIEW_FOCUSED"}, {"category": "", "app": "Chrome", "id": "163", "context": "臺北站介紹   》 臺北站介紹  ", "time": "2017/07/07 17:41:32", "event": "TYPE_VIEW_CLICKED"}, {"category": "", "app": "Chrome", "id": "164", "context": "台北車站 www.railway.gov.tw", "time": "2017/07/07 17:41:33", "event": "TYPE_VIEW_SCROLLED"}, {"category": "", "app": "Chrome", "id": "165", "context": "http://www.railway.gov.tw/taipei/index.aspx# ", "time": "2017/07/07 17:41:34", "event": "TYPE_VIEW_FOCUSED"}, {"category": "", "app": "Chrome", "id": "166", "context": "搜尋或輸入網址  ", "time": "2017/07/07 17:41:34", "event": "TYPE_VIEW_TEXT_CHANGED"}, {"category": "", "app": "Chrome", "id": "167", "context": "ㄒ  ", "time": "2017/07/07 17:41:41", "event": "TYPE_VIEW_TEXT_CHANGED"}, {"category": "", "app": "Chrome", "id": "168", "context": "ㄒㄧ  ", "time": "2017/07/07 17:41:41", "event": "TYPE_VIEW_TEXT_CHANGED"}, {"category": "", "app": "Chrome", "id": "169", "context": "ㄒㄧㄤ  ", "time": "2017/07/07 17:41:41", "event": "TYPE_VIEW_TEXT_CHANGED"}, {"category": "", "app": "Chrome", "id": "170", "context": "ㄒㄧㄤˋ  ", "time": "2017/07/07 17:41:43", "event": "TYPE_VIEW_TEXT_CHANGED"}, {"category": "", "app": "Chrome", "id": "171", "context": "象  ", "time": "2017/07/07 17:41:44", "event": "TYPE_VIEW_TEXT_CHANGED"}, {"category": "", "app": "Chrome", "id": "172", "context": "象ㄕ  ", "time": "2017/07/07 17:41:45", "event": "TYPE_VIEW_TEXT_CHANGED"}, {"category": "", "app": "Chrome", "id": "173", "context": "象ㄕㄢ  ", "time": "2017/07/07 17:41:45", "event": "TYPE_VIEW_TEXT_CHANGED"}, {"category": "", "app": "Chrome", "id": "174", "context": "象山  ", "time": "2017/07/07 17:41:46", "event": "TYPE_VIEW_TEXT_CHANGED"}, {"category": "", "app": "Chrome", "id": "175", "context": "象山 - Google 搜尋 https://www.google.com.tw/search?q=象山&oq=象山&aqs=chrome..69i57j0j5j0.5068j0j4&client=ms-android-sonymobile&sourceid=chrome-mobile&ie=UTF-8", "time": "2017/07/07 17:41:47", "event": "TYPE_VIEW_SCROLLED"}, {"category": "", "app": "Chrome", "id": "176", "context": "https://www.google.com.tw/search?q=%E8%B1%A1%E5%B1%B1&oq=%E8%B1%A1%E5%B1%B1&aqs=chrome..69i57j0j5j0.5068j0j4&client=ms-android-sonymobile&sourceid=chrome-mobile&ie=UTF-8 ", "time": "2017/07/07 17:41:48", "event": "TYPE_VIEW_FOCUSED"}, {"category": "", "app": "Chrome", "id": "177", "context": "搜尋或輸入網址  ", "time": "2017/07/07 17:41:48", "event": "TYPE_VIEW_TEXT_CHANGED"}, {"category": "", "app": "Chrome", "id": "178", "context": "ㄇ  ", "time": "2017/07/07 17:41:50", "event": "TYPE_VIEW_TEXT_CHANGED"}, {"category": "", "app": "Chrome", "id": "179", "context": "ㄇㄨ  ", "time": "2017/07/07 17:41:50", "event": "TYPE_VIEW_TEXT_CHANGED"}, {"category": "", "app": "Chrome", "id": "180", "context": "ㄇㄨㄓ  ", "time": "2017/07/07 17:41:51", "event": "TYPE_VIEW_TEXT_CHANGED"}, {"category": "", "app": "Chrome", "id": "181", "context": "ㄇㄨㄓㄚ  ", "time": "2017/07/07 17:41:51", "event": "TYPE_VIEW_TEXT_CHANGED"}, {"category": "", "app": "Chrome", "id": "182", "context": "木柵  ", "time": "2017/07/07 17:41:51", "event": "TYPE_VIEW_TEXT_CHANGED"}, {"category": "", "app": "Chrome", "id": "183", "context": "木柵 - Google 搜尋 https://www.google.com.tw/search?q=木柵&oq=木柵&aqs=chrome..69i57j0j5j0j69i61l2.2381j0j4&client=ms-android-sonymobile&sourceid=chrome-mobile&ie=UTF-8", "time": "2017/07/07 17:41:56", "event": "TYPE_VIEW_SCROLLED"}, {"category": "", "app": "Chrome", "id": "184", "context": "臺北市立動物園 ", "time": "2017/07/07 17:41:59", "event": "TYPE_VIEW_FOCUSED"}, {"category": "", "app": "Chrome", "id": "185", "context": "臺北市立動物園  ", "time": "2017/07/07 17:41:59", "event": "TYPE_VIEW_CLICKED"}, {"category": "", "app": "Chrome", "id": "186", "context": "木柵 - Google 搜尋 https://www.google.com.tw", "time": "2017/07/07 17:41:59", "event": "TYPE_VIEW_SCROLLED"}, {"category": "", "app": "Chrome", "id": "187", "context": "臺北市立動物園 www.zoo.gov.taipei", "time": "2017/07/07 17:42:00", "event": "TYPE_VIEW_SCROLLED"}, {"category": "", "app": "Chrome", "id": "188", "context": "http://www.zoo.gov.taipei/ ", "time": "2017/07/07 17:42:16", "event": "TYPE_VIEW_FOCUSED"}, {"category": "", "app": "Chrome", "id": "189", "context": "搜尋或輸入網址  ", "time": "2017/07/07 17:42:17", "event": "TYPE_VIEW_TEXT_CHANGED"}, {"category": "", "app": "Chrome", "id": "190", "context": "ㄊ  ", "time": "2017/07/07 17:42:27", "event": "TYPE_VIEW_TEXT_CHANGED"}, {"category": "", "app": "Chrome", "id": "191", "context": "ㄊㄞ  ", "time": "2017/07/07 17:42:27", "event": "TYPE_VIEW_TEXT_CHANGED"}, {"category": "", "app": "Chrome", "id": "192", "context": "ㄊㄞㄅ  ", "time": "2017/07/07 17:42:27", "event": "TYPE_VIEW_TEXT_CHANGED"}, {"category": "", "app": "Chrome", "id": "193", "context": "台北  ", "time": "2017/07/07 17:42:28", "event": "TYPE_VIEW_TEXT_CHANGED"}, {"category": "", "app": "Chrome", "id": "194", "context": "台北101  ", "time": "2017/07/07 17:42:29", "event": "TYPE_VIEW_TEXT_CHANGED"}, {"category": "", "app": "Chrome", "id": "195", "context": "台北101 - Google 搜尋 https://www.google.com.tw/search?q=台北101&oq=台北101&aqs=chrome.0.69i59j0j5j69i61.2542j0j4&client=ms-android-sonymobile&sourceid=chrome-mobile&ie=UTF-8", "time": "2017/07/07 17:42:30", "event": "TYPE_VIEW_SCROLLED"}, {"category": "", "app": "Chrome", "id": "196", "context": "更多台北101的相關資訊  ", "time": "2017/07/07 17:42:33", "event": "TYPE_VIEW_CLICKED"}, {"category": "", "app": "Chrome", "id": "197", "context": "台北101官方網站 ", "time": "2017/07/07 17:42:35", "event": "TYPE_VIEW_FOCUSED"}, {"category": "", "app": "Chrome", "id": "198", "context": "101 Taipei Financial Center Corp. 台北101官方網站 www.taipei-101.com.tw/m/", "time": "2017/07/07 17:42:37", "event": "TYPE_VIEW_SCROLLED"}, {"category": "", "app": "Chrome", "id": "199", "context": "101 Taipei Financial Center Corp. 台北101官方網站 www.taipei-101.com.tw", "time": "2017/07/07 17:42:53", "event": "TYPE_VIEW_SCROLLED"}, {"category": "", "app": "Chrome", "id": "200", "context": "http://www.taipei-101.com.tw/m/ ", "time": "2017/07/07 17:42:59", "event": "TYPE_VIEW_FOCUSED"}, {"category": "", "app": "Chrome", "id": "201", "context": "搜尋或輸入網址  ", "time": "2017/07/07 17:42:59", "event": "TYPE_VIEW_TEXT_CHANGED"}, {"category": "", "app": "Chrome", "id": "202", "context": "ㄙ  ", "time": "2017/07/07 17:43:04", "event": "TYPE_VIEW_TEXT_CHANGED"}, {"category": "", "app": "Chrome", "id": "203", "context": "ㄙㄨ  ", "time": "2017/07/07 17:43:04", "event": "TYPE_VIEW_TEXT_CHANGED"}, {"category": "", "app": "Chrome", "id": "204", "context": "ㄙ  ", "time": "2017/07/07 17:43:04", "event": "TYPE_VIEW_TEXT_CHANGED"}, {"category": "", "app": "Chrome", "id": "205", "context": "搜尋或輸入網址  ", "time": "2017/07/07 17:43:05", "event": "TYPE_VIEW_TEXT_CHANGED"}, {"category": "", "app": "Chrome", "id": "206", "context": "ㄏ  ", "time": "2017/07/07 17:43:05", "event": "TYPE_VIEW_TEXT_CHANGED"}, {"category": "", "app": "Chrome", "id": "207", "context": "ㄏㄨ  ", "time": "2017/07/07 17:43:05", "event": "TYPE_VIEW_TEXT_CHANGED"}, {"category": "", "app": "Chrome", "id": "208", "context": "ㄏㄨㄚ  ", "time": "2017/07/07 17:43:05", "event": "TYPE_VIEW_TEXT_CHANGED"}, {"category": "", "app": "Chrome", "id": "209", "context": "ㄏㄨㄚㄕ  ", "time": "2017/07/07 17:43:05", "event": "TYPE_VIEW_TEXT_CHANGED"}, {"category": "", "app": "Chrome", "id": "210", "context": "華山  ", "time": "2017/07/07 17:43:06", "event": "TYPE_VIEW_TEXT_CHANGED"}, {"category": "", "app": "Chrome", "id": "211", "context": "華山文創園區 - Google 搜尋 https://www.google.com.tw/search?q=華山文創園區&oq=華山&aqs=chrome.1.69i59j0j5j69i61.2243j0j4&client=ms-android-sonymobile&sourceid=chrome-mobile&ie=UTF-8", "time": "2017/07/07 17:43:09", "event": "TYPE_VIEW_SCROLLED"}, {"category": "", "app": "Chrome", "id": "212", "context": "華山文創園區 - Google 搜尋 https://www.google.com.tw", "time": "2017/07/07 17:43:10", "event": "TYPE_VIEW_SCROLLED"}, {"category": "", "app": "Chrome", "id": "213", "context": "華山1914文化創意產業園區 ", "time": "2017/07/07 17:43:16", "event": "TYPE_VIEW_FOCUSED"}, {"category": "", "app": "Chrome", "id": "214", "context": "華山1914文化創意產業園區  ", "time": "2017/07/07 17:43:16", "event": "TYPE_VIEW_CLICKED"}, {"category": "", "app": "Chrome", "id": "215", "context": "華山文創園區 - Google 搜尋 https://www.google.com.tw", "time": "2017/07/07 17:43:16", "event": "TYPE_VIEW_SCROLLED"}, {"category": "", "app": "Chrome", "id": "216", "context": "華山文創園區 - Google 搜尋 www.huashan1914.com", "time": "2017/07/07 17:43:16", "event": "TYPE_VIEW_SCROLLED"}, {"category": "", "app": "Chrome", "id": "217", "context": ":: 華山1914文化創意產業園區 :: www.huashan1914.com", "time": "2017/07/07 17:43:17", "event": "TYPE_VIEW_SCROLLED"}, {"category": "", "app": "Chrome", "id": "218", "context": ":: 華山1914文化創意產業園區 :: https://www.google.com.tw", "time": "2017/07/07 17:43:21", "event": "TYPE_VIEW_SCROLLED"}, {"category": "", "app": "Chrome", "id": "219", "context": "華山文創園區 - Google 搜尋 https://www.google.com.tw", "time": "2017/07/07 17:43:21", "event": "TYPE_VIEW_SCROLLED"}, {"category": "", "app": "Chrome", "id": "220", "context": "[ 台北好玩] 華山1914文化創意園區@ bobowin旅行攝影生活:: 隨意窩Xuite日誌 ", "time": "2017/07/07 17:43:23", "event": "TYPE_VIEW_FOCUSED"}, {"category": "", "app": "Chrome", "id": "221", "context": "[ 台北好玩] 華山1914文化創意園區@ bobowin旅行攝影生活:: 隨意窩Xuite日誌  ", "time": "2017/07/07 17:43:23", "event": "TYPE_VIEW_CLICKED"}, {"category": "", "app": "Chrome", "id": "222", "context": "[ 台北好玩 ] 華山1914文化創意園區 @ bobowin旅行攝影生活 :: 隨意窩 Xuite日誌 m.xuite.net/blog/bobowin/me/44755062", "time": "2017/07/07 17:43:25", "event": "TYPE_VIEW_SCROLLED"}, {"category": "", "app": "Chrome", "id": "223", "context": "[ 台北好玩 ] 華山1914文化創意園區 @ bobowin旅行攝影生活 :: 隨意窩 Xuite日誌 m.xuite.net", "time": "2017/07/07 17:43:45", "event": "TYPE_VIEW_SCROLLED"}, {"category": "", "app": "Chrome", "id": "224", "context": "華山文創園區 - Google 搜尋 https://www.google.com.tw/search?q=華山文創園區&oq=華山&aqs=chrome.1.69i59j0j5j69i61.2243j0j4&client=ms-android-sonymobile&sourceid=chrome-mobile&ie=UTF-8", "time": "2017/07/07 17:43:46", "event": "TYPE_VIEW_SCROLLED"}, {"category": "", "app": "Chrome", "id": "225", "context": "華山文創園區 - Google 搜尋 https://www.google.com.tw", "time": "2017/07/07 17:44:02", "event": "TYPE_VIEW_SCROLLED"}, {"category": "", "app": "Chrome", "id": "226", "context": "華山文創園區 - Google 搜尋 https://www.google.com.tw/search?q=%E8%8F%AF%E5%B1%B1%E6%96%87%E5%89%B5%E5%9C%92%E5%8D%80&oq=%E8%8F%AF%E5%B1%B1&aqs=chrome.1.69i59j0j5j69i61.2243j0j4&client=ms-android-sonymobile&sourceid=chrome-mobile&ie=UTF-8", "time": "2017/07/07 17:44:03", "event": "TYPE_VIEW_SCROLLED"}, {"category": "", "app": "Chrome", "id": "227", "context": "https://www.google.com.tw/search?q=%E8%8F%AF%E5%B1%B1%E6%96%87%E5%89%B5%E5%9C%92%E5%8D%80&oq=%E8%8F%AF%E5%B1%B1&aqs=chrome.1.69i59j0j5j69i61.2243j0j4&client=ms-android-sonymobile&sourceid=chrome-mobile&ie=UTF-8 ", "time": "2017/07/07 17:44:03", "event": "TYPE_VIEW_FOCUSED"}, {"category": "", "app": "Chrome", "id": "228", "context": "ㄖ  ", "time": "2017/07/07 17:44:13", "event": "TYPE_VIEW_TEXT_CHANGED"}, {"category": "", "app": "Chrome", "id": "229", "context": "ㄖㄠ  ", "time": "2017/07/07 17:44:13", "event": "TYPE_VIEW_TEXT_CHANGED"}, {"category": "", "app": "Chrome", "id": "230", "context": "ㄖㄠㄏ  ", "time": "2017/07/07 17:44:14", "event": "TYPE_VIEW_TEXT_CHANGED"}, {"category": "", "app": "Chrome", "id": "231", "context": "饒河夜市  ", "time": "2017/07/07 17:44:14", "event": "TYPE_VIEW_TEXT_CHANGED"}, {"category": "", "app": "Chrome", "id": "232", "context": "饒河夜市 - Google 搜尋 https://www.google.com.tw/search?q=饒河夜市&oq=饒河&aqs=chrome.0.69i59j69i57j0l2j69i60l2.1644j0j4&client=ms-android-sonymobile&sourceid=chrome-mobile&ie=UTF-8", "time": "2017/07/07 17:44:15", "event": "TYPE_VIEW_SCROLLED"}, {"category": "", "app": "Chrome", "id": "233", "context": "饒河夜市 - Google 搜尋 https://www.google.com.tw", "time": "2017/07/07 17:44:18", "event": "TYPE_VIEW_SCROLLED"}, {"category": "", "app": "Chrome", "id": "234", "context": "[懶人包] 貓大爺饒河街夜市美食攻略(18篇) 1258 @ 貓大爺部落格:: 隨意窩 ... ", "time": "2017/07/07 17:44:20", "event": "TYPE_VIEW_FOCUSED"}, {"category": "", "app": "Chrome", "id": "235", "context": "[懶人包] 貓大爺饒河街夜市美食攻略(18篇) 1258 @ 貓大爺部落格:: 隨意窩 ...  ", "time": "2017/07/07 17:44:20", "event": "TYPE_VIEW_CLICKED"}, {"category": "", "app": "Chrome", "id": "236", "context": "[懶人包] 貓大爺饒河街夜市美食攻略 (18篇) 1258 @ 貓大爺部落格 :: 隨意窩 Xuite日誌 m.xuite.net/blog/maomi/Food01/63959857", "time": "2017/07/07 17:44:21", "event": "TYPE_VIEW_SCROLLED"}, {"category": "", "app": "com.sonyericsson.home", "id": "237", "context": "主畫面5之2  ", "time": "2017/07/07 17:44:47", "event": "TYPE_VIEW_CLICKED"}, {"category": "", "app": "com.android.systemui", "id": "238", "context": "行動數據連線  ", "time": "2017/07/07 17:45:06", "event": "TYPE_VIEW_CLICKED"}, {"category": "", "app": "com.android.systemui", "id": "239", "context": "已關閉Wi-Fi。  ", "time": "2017/07/07 17:45:10", "event": "TYPE_VIEW_CLICKED"}, {"category": "", "app": "Facebook", "id": "240", "context": "【反骨有嘻哈】你今天有FREE STYLE嗎… 查看更多 ", "time": "2017/07/07 17:45:15", "event": "TYPE_VIEW_SCROLLED"}, {"category": "", "app": "Facebook", "id": "241", "context": "video player ", "time": "2017/07/07 17:45:17", "event": "TYPE_VIEW_FOCUSED"}, {"category": "", "app": "Facebook", "id": "242", "context": "【反骨有嘻哈】你今天有FREE STYLE嗎… 查看更多 ", "time": "2017/07/07 17:45:18", "event": "TYPE_VIEW_SCROLLED"}, {"category": "", "app": "Facebook", "id": "243", "context": "video player ", "time": "2017/07/07 17:45:20", "event": "TYPE_VIEW_FOCUSED"}, {"category": "", "app": "Facebook", "id": "244", "context": "已選擇，通知  ", "time": "2017/07/07 17:47:51", "event": "TYPE_VIEW_CLICKED"}, {"category": "", "app": "Facebook", "id": "245", "context": "回覆…… ", "time": "2017/07/07 17:48:05", "event": "TYPE_VIEW_FOCUSED"}, {"category": "", "app": "Facebook", "id": "246", "context": "E  ", "time": "2017/07/07 17:48:10", "event": "TYPE_VIEW_TEXT_CHANGED"}, {"category": "", "app": "Facebook", "id": "247", "context": "EX  ", "time": "2017/07/07 17:48:10", "event": "TYPE_VIEW_TEXT_CHANGED"}, {"category": "", "app": "Facebook", "id": "248", "context": "EXO  ", "time": "2017/07/07 17:48:10", "event": "TYPE_VIEW_TEXT_CHANGED"}, {"category": "", "app": "Facebook", "id": "249", "context": "EXOㄐ  ", "time": "2017/07/07 17:48:12", "event": "TYPE_VIEW_TEXT_CHANGED"}, {"category": "", "app": "Facebook", "id": "250", "context": "EXOㄐㄧ  ", "time": "2017/07/07 17:48:12", "event": "TYPE_VIEW_TEXT_CHANGED"}, {"category": "", "app": "Facebook", "id": "251", "context": "EXOㄐㄧㄤ  ", "time": "2017/07/07 17:48:12", "event": "TYPE_VIEW_TEXT_CHANGED"}, {"category": "", "app": "Facebook", "id": "252", "context": "EXO醬  ", "time": "2017/07/07 17:48:13", "event": "TYPE_VIEW_TEXT_CHANGED"}, {"category": "", "app": "Facebook", "id": "253", "context": "貼圖  ", "time": "2017/07/07 17:48:13", "event": "TYPE_VIEW_CLICKED"}, {"category": "", "app": "Facebook", "id": "254", "context": "讚 ", "time": "2017/07/07 17:48:34", "event": "TYPE_VIEW_FOCUSED"}, {"category": "", "app": "Facebook", "id": "255", "context": "讚  ", "time": "2017/07/07 17:48:34", "event": "TYPE_VIEW_CLICKED"}, {"category": "", "app": "Facebook", "id": "256", "context": "讚 ", "time": "2017/07/07 17:48:35", "event": "TYPE_VIEW_FOCUSED"}, {"category": "", "app": "Facebook", "id": "257", "context": "讚  ", "time": "2017/07/07 17:49:23", "event": "TYPE_VIEW_CLICKED"}, {"category": "", "app": "Facebook", "id": "258", "context": "讚 ", "time": "2017/07/07 17:49:23", "event": "TYPE_VIEW_FOCUSED"}, {"category": "", "app": "com.android.systemui", "id": "259", "context": "[懶人包] 貓大爺饒河街夜市美食攻略 (18篇) 1258 @ 貓大爺部落格 :: 隨意窩 Xuite日誌  ", "time": "2017/07/07 17:50:03", "event": "TYPE_VIEW_CLICKED"}, {"category": "", "app": "com.android.systemui", "id": "260", "context": "[懶人包] 貓大爺饒河街夜市美食攻略 (18篇) 1258 @ 貓大爺部落格 :: 隨意窩 Xuite日誌  關閉「[懶人包] 貓大爺饒河街夜市美食攻略 (18篇) 1258 @ 貓大爺部落格 :: 隨意窩 Xuite日誌」。  ", "time": "2017/07/07 17:50:15", "event": "TYPE_VIEW_CLICKED"}, {"category": "", "app": "Chrome", "id": "261", "context": "[懶人包] 貓大爺饒河街夜市美食攻略 (18篇) 1258 @ 貓大爺部落格 :: 隨意窩 Xuite日誌 m.xuite.net", "time": "2017/07/07 17:50:17", "event": "TYPE_VIEW_SCROLLED"}, {"category": "", "app": "com.android.systemui", "id": "262", "context": "｜台北旅遊指南｜2017必去台北景點、美食及台北住宿攻略｜AsiaYo  ", "time": "2017/07/07 17:50:20", "event": "TYPE_VIEW_CLICKED"}, {"category": "", "app": "Chrome", "id": "263", "context": "｜台北旅遊指南｜2017必去台北景點、美食及台北住宿攻略｜AsiaYo https://asiayo.com", "time": "2017/07/07 17:50:26", "event": "TYPE_VIEW_SCROLLED"}, {"category": "", "app": "Chrome", "id": "264", "context": "https://asiayo.com/event/taipei_fit.html ", "time": "2017/07/07 17:50:27", "event": "TYPE_VIEW_FOCUSED"}, {"category": "", "app": "Chrome", "id": "265", "context": "ㄇ  ", "time": "2017/07/07 17:50:30", "event": "TYPE_VIEW_TEXT_CHANGED"}, {"category": "", "app": "Chrome", "id": "266", "context": "ㄇㄟ  ", "time": "2017/07/07 17:50:30", "event": "TYPE_VIEW_TEXT_CHANGED"}, {"category": "", "app": "Chrome", "id": "267", "context": "美  ", "time": "2017/07/07 17:50:31", "event": "TYPE_VIEW_TEXT_CHANGED"}, {"category": "", "app": "Chrome", "id": "268", "context": "美ㄌ  ", "time": "2017/07/07 17:50:31", "event": "TYPE_VIEW_TEXT_CHANGED"}, {"category": "", "app": "Chrome", "id": "269", "context": "美ㄌㄧ  ", "time": "2017/07/07 17:50:31", "event": "TYPE_VIEW_TEXT_CHANGED"}, {"category": "", "app": "Chrome", "id": "270", "context": "美ㄌㄧˋ  ", "time": "2017/07/07 17:50:32", "event": "TYPE_VIEW_TEXT_CHANGED"}, {"category": "", "app": "Chrome", "id": "271", "context": "美麗  ", "time": "2017/07/07 17:50:33", "event": "TYPE_VIEW_TEXT_CHANGED"}, {"category": "", "app": "Chrome", "id": "272", "context": "美麗ㄏ  ", "time": "2017/07/07 17:50:34", "event": "TYPE_VIEW_TEXT_CHANGED"}, {"category": "", "app": "Chrome", "id": "273", "context": "美麗ㄏㄨ  ", "time": "2017/07/07 17:50:34", "event": "TYPE_VIEW_TEXT_CHANGED"}, {"category": "", "app": "Chrome", "id": "274", "context": "美麗ㄏㄨㄚ  ", "time": "2017/07/07 17:50:34", "event": "TYPE_VIEW_TEXT_CHANGED"}, {"category": "", "app": "Chrome", "id": "275", "context": "美麗華  ", "time": "2017/07/07 17:50:35", "event": "TYPE_VIEW_TEXT_CHANGED"}, {"category": "", "app": "Chrome", "id": "276", "context": "美麗華 - Google 搜尋 https://www.google.com.tw/search?q=美麗華&oq=美麗華&aqs=chrome..69i57j0j5j0.5959j0j4&client=ms-android-sonymobile&sourceid=chrome-mobile&ie=UTF-8", "time": "2017/07/07 17:50:37", "event": "TYPE_VIEW_SCROLLED"}, {"category": "", "app": "Chrome", "id": "277", "context": "美麗華影城 ", "time": "2017/07/07 17:50:46", "event": "TYPE_VIEW_FOCUSED"}, {"category": "", "app": "Chrome", "id": "278", "context": "美麗華影城  ", "time": "2017/07/07 17:50:46", "event": "TYPE_VIEW_CLICKED"}, {"category": "", "app": "Chrome", "id": "279", "context": "美麗華 - Google 搜尋 https://www.miramarcinemas.com.tw", "time": "2017/07/07 17:50:46", "event": "TYPE_VIEW_SCROLLED"}, {"category": "", "app": "Chrome", "id": "280", "context": "美麗華影城 https://www.miramarcinemas.com.tw", "time": "2017/07/07 17:50:48", "event": "TYPE_VIEW_SCROLLED"}, {"category": "", "app": "Chrome", "id": "281", "context": "美麗華 - Google 搜尋 https://www.google.com.tw/search?q=美麗華&oq=美麗華&aqs=chrome..69i57j0j5j0.5959j0j4&client=ms-android-sonymobile&sourceid=chrome-mobile&ie=UTF-8", "time": "2017/07/07 17:51:35", "event": "TYPE_VIEW_SCROLLED"}, {"category": "", "app": "Chrome", "id": "282", "context": "美麗華 - Google 搜尋 https://www.google.com.tw", "time": "2017/07/07 17:51:38", "event": "TYPE_VIEW_SCROLLED"}, {"category": "", "app": "Chrome", "id": "283", "context": "下一頁 ", "time": "2017/07/07 17:51:46", "event": "TYPE_VIEW_FOCUSED"}, {"category": "", "app": "Chrome", "id": "284", "context": "美麗華 - Google 搜尋 https://www.google.com.tw/search?q=美麗華&client=ms-android-sonymobile&prmd=minv&ei=allfWYTEBoWq0ATAroa4BA&start=10&sa=N&biw=480&bih=780", "time": "2017/07/07 17:51:47", "event": "TYPE_VIEW_SCROLLED"}, {"category": "", "app": "Chrome", "id": "285", "context": "美麗華 - Google 搜尋 https://www.google.com.tw", "time": "2017/07/07 17:51:50", "event": "TYPE_VIEW_SCROLLED"}, {"category": "", "app": "Chrome", "id": "286", "context": "美麗華 ", "time": "2017/07/07 17:51:55", "event": "TYPE_VIEW_FOCUSED"}, {"category": "", "app": "Chrome", "id": "287", "context": "美麗華  ", "time": "2017/07/07 17:51:55", "event": "TYPE_VIEW_CLICKED"}, {"category": "", "app": "Chrome", "id": "288", "context": "美麗華 - Google 搜尋 https://www.google.com.tw", "time": "2017/07/07 17:51:55", "event": "TYPE_VIEW_SCROLLED"}, {"category": "", "app": "Chrome", "id": "289", "context": "美麗華 鬼屋 - Google 搜尋 https://www.google.com.tw/search?client=ms-android-sonymobile&biw=480&bih=394&ei=sFlfWYaZNcua0gTF2qDgDg&q=美麗華+鬼屋&oq=美麗華+鬼&gs_l=mobile-gws-serp.1.1.0i30k1l2j0i8i30k1.7688.9541.0.12505.5.5.0.0.0.0.283.637.3j1j1.5.0....0...1.1j4.64.mobile-gws-serp..0.2.376...0.qwY-DjfRc1o", "time": "2017/07/07 17:52:02", "event": "TYPE_VIEW_SCROLLED"}, {"category": "", "app": "Chrome", "id": "290", "context": "美麗華 鬼屋 ", "time": "2017/07/07 17:52:06", "event": "TYPE_VIEW_FOCUSED"}, {"category": "", "app": "Chrome", "id": "291", "context": "美麗華 鬼屋  ", "time": "2017/07/07 17:52:06", "event": "TYPE_VIEW_CLICKED"}, {"category": "", "app": "Chrome", "id": "292", "context": "美麗華 鬼屋 - Google 搜尋 https://www.google.com.tw", "time": "2017/07/07 17:52:06", "event": "TYPE_VIEW_SCROLLED"}, {"category": "", "app": "Chrome", "id": "293", "context": "美麗華 鬼故事 - Google 搜尋 https://www.google.com.tw/search?client=ms-android-sonymobile&biw=480&bih=394&ei=v1lfWeebHsiY0gSUu66gDg&q=美麗華+鬼故事&oq=美麗華+鬼故事&gs_l=mobile-gws-serp.3...3871.6552.0.7600.5.5.0.0.0.0.203.601.3j1j1.5.0....0...1.1j4.64.mobile-gws-serp..0.1.186...41j0i30k1j0i8i30k1.MP80VRXR1I0", "time": "2017/07/07 17:52:11", "event": "TYPE_VIEW_SCROLLED"}, {"category": "", "app": "Chrome", "id": "294", "context": "美麗華 鬼故事 ", "time": "2017/07/07 17:52:17", "event": "TYPE_VIEW_FOCUSED"}, {"category": "", "app": "Chrome", "id": "295", "context": "美麗華 鬼故事  ", "time": "2017/07/07 17:52:17", "event": "TYPE_VIEW_CLICKED"}, {"category": "", "app": "Chrome", "id": "296", "context": "美麗華 鬼故事 - Google 搜尋 https://www.google.com.tw", "time": "2017/07/07 17:52:17", "event": "TYPE_VIEW_SCROLLED"}, {"category": "", "app": "Chrome", "id": "297", "context": "美麗華 影城 - Google 搜尋 https://www.google.com.tw/search?client=ms-android-sonymobile&biw=480&bih=394&ei=yVlfWciMFMa10AS_j4_gBw&q=美麗華+影城&oq=美麗華+&gs_l=mobile-gws-serp.1.3.41l2j0l3.5096.5600.0.9934.3.3.0.0.0.0.152.351.1j2.3.0....0...1.1j4.64.mobile-gws-serp..0.3.346...0i30k1j0i8i30k1.RlRCLDI5Qoo", "time": "2017/07/07 17:52:24", "event": "TYPE_VIEW_SCROLLED"}, {"category": "", "app": "Chrome", "id": "298", "context": "美麗華 影城 ", "time": "2017/07/07 17:52:29", "event": "TYPE_VIEW_FOCUSED"}, {"category": "", "app": "Chrome", "id": "299", "context": "美麗華 影城  ", "time": "2017/07/07 17:52:29", "event": "TYPE_VIEW_CLICKED"}, {"category": "", "app": "Chrome", "id": "300", "context": "美麗華 影城 - Google 搜尋 https://www.google.com.tw", "time": "2017/07/07 17:52:30", "event": "TYPE_VIEW_SCROLLED"}, {"category": "", "app": "Chrome", "id": "301", "context": "國泰信用卡 - Google 搜尋 https://www.google.com.tw/search?client=ms-android-sonymobile&biw=480&bih=394&ei=1VlfWdDrJcu00AT34p_AAQ&q=國泰信用卡&oq=國泰&gs_l=mobile-gws-serp.1.4.0l5.17972.31192.0.33335.19.16.1.1.1.0.256.2328.3j12j1.16.0....0...1.1j4.64.mobile-gws-serp..3.13.1758.3..41.t2P_5BPHc4s", "time": "2017/07/07 17:53:00", "event": "TYPE_VIEW_SCROLLED"}, {"category": "", "app": "Chrome", "id": "302", "context": "國泰信用卡 - Google 搜尋 https://www.google.com.tw", "time": "2017/07/07 17:53:45", "event": "TYPE_VIEW_SCROLLED"}, {"category": "", "app": "Chrome", "id": "303", "context": "國泰信用卡 ", "time": "2017/07/07 17:53:47", "event": "TYPE_VIEW_FOCUSED"}, {"category": "", "app": "Chrome", "id": "304", "context": "國泰信用卡  ", "time": "2017/07/07 17:53:47", "event": "TYPE_VIEW_CLICKED"}, {"category": "", "app": "Chrome", "id": "305", "context": "國泰信用卡 - Google 搜尋 https://www.google.com.tw", "time": "2017/07/07 17:53:47", "event": "TYPE_VIEW_SCROLLED"}, {"category": "", "app": "Chrome", "id": "306", "context": "國泰 visa - Google 搜尋 https://www.google.com.tw/search?client=ms-android-sonymobile&biw=480&bih=394&ei=-VlfWbL4LcSd0gTbqYeYAw&q=國泰+visa&oq=國泰+visa&gs_l=mobile-gws-serp.3..0l4j0i30k1.46352.57830.0.58135.10.8.2.0.0.0.198.1091.0j8.8.0....0...1.1j4.64.mobile-gws-serp..0.10.1172...41j0i131k1.s9_-MBNSCwg", "time": "2017/07/07 17:54:00", "event": "TYPE_VIEW_SCROLLED"}, {"category": "", "app": "Chrome", "id": "307", "context": "i 刷金融卡- 信用卡介紹- 信用卡- 國泰世華銀行 ", "time": "2017/07/07 17:54:05", "event": "TYPE_VIEW_FOCUSED"}, {"category": "", "app": "Chrome", "id": "308", "context": "i 刷金融卡- 信用卡介紹- 信用卡- 國泰世華銀行  ", "time": "2017/07/07 17:54:05", "event": "TYPE_VIEW_CLICKED"}, {"category": "", "app": "Chrome", "id": "309", "context": "國泰 visa - Google 搜尋 https://www.cathaybk.com.tw/cathaybk/personal/credit-card/cards/intro/i-debit/", "time": "2017/07/07 17:54:07", "event": "TYPE_VIEW_SCROLLED"}, {"category": "", "app": "Chrome", "id": "310", "context": "i 刷金融卡 - 信用卡介紹 - 信用卡 - 國泰世華銀行 https://www.cathaybk.com.tw", "time": "2017/07/07 17:54:20", "event": "TYPE_VIEW_SCROLLED"}, {"category": "", "app": "Chrome", "id": "311", "context": " 專屬優惠 ", "time": "2017/07/07 17:54:35", "event": "TYPE_VIEW_FOCUSED"}, {"category": "", "app": "Chrome", "id": "312", "context": " 專屬優惠  ", "time": "2017/07/07 17:54:35", "event": "TYPE_VIEW_CLICKED"}, {"category": "", "app": "Chrome", "id": "313", "context": "i 刷金融卡 - 信用卡介紹 - 信用卡 - 國泰世華銀行 https://www.cathaybk.com.tw", "time": "2017/07/07 17:54:37", "event": "TYPE_VIEW_SCROLLED"}, {"category": "", "app": "Chrome", "id": "314", "context": " 其他說明 ", "time": "2017/07/07 17:55:06", "event": "TYPE_VIEW_FOCUSED"}, {"category": "", "app": "Chrome", "id": "315", "context": " 其他說明  ", "time": "2017/07/07 17:55:07", "event": "TYPE_VIEW_CLICKED"}, {"category": "", "app": "Chrome", "id": "316", "context": "i 刷金融卡 - 信用卡介紹 - 信用卡 - 國泰世華銀行 https://www.cathaybk.com.tw", "time": "2017/07/07 17:55:22", "event": "TYPE_VIEW_SCROLLED"}, {"category": "", "app": "Chrome", "id": "317", "context": " 常見問題 ", "time": "2017/07/07 17:56:38", "event": "TYPE_VIEW_FOCUSED"}, {"category": "", "app": "Chrome", "id": "318", "context": " 常見問題  ", "time": "2017/07/07 17:56:39", "event": "TYPE_VIEW_CLICKED"}, {"category": "", "app": "Chrome", "id": "319", "context": "i 刷金融卡 - 信用卡介紹 - 信用卡 - 國泰世華銀行 https://www.cathaybk.com.tw", "time": "2017/07/07 17:56:44", "event": "TYPE_VIEW_SCROLLED"}, {"category": "", "app": "Chrome", "id": "320", "context": "https://www.cathaybk.com.tw/cathaybk/personal/credit-card/cards/intro/i-debit/#tab-05 ", "time": "2017/07/07 17:58:03", "event": "TYPE_VIEW_FOCUSED"}, {"category": "", "app": "Chrome", "id": "321", "context": "ㄧ  ", "time": "2017/07/07 17:58:08", "event": "TYPE_VIEW_TEXT_CHANGED"}, {"category": "", "app": "Chrome", "id": "322", "context": "ㄧㄡ  ", "time": "2017/07/07 17:58:08", "event": "TYPE_VIEW_TEXT_CHANGED"}, {"category": "", "app": "Chrome", "id": "323", "context": "ㄧㄡㄐ  ", "time": "2017/07/07 17:58:09", "event": "TYPE_VIEW_TEXT_CHANGED"}, {"category": "", "app": "Chrome", "id": "324", "context": "ㄧㄡㄐㄩ  ", "time": "2017/07/07 17:58:09", "event": "TYPE_VIEW_TEXT_CHANGED"}, {"category": "", "app": "Chrome", "id": "325", "context": "郵局  ", "time": "2017/07/07 17:58:10", "event": "TYPE_VIEW_TEXT_CHANGED"}, {"category": "", "app": "Chrome", "id": "326", "context": "郵局ㄏ  ", "time": "2017/07/07 17:58:11", "event": "TYPE_VIEW_TEXT_CHANGED"}, {"category": "", "app": "Chrome", "id": "327", "context": "郵局ㄏㄨ  ", "time": "2017/07/07 17:58:11", "event": "TYPE_VIEW_TEXT_CHANGED"}, {"category": "", "app": "Chrome", "id": "328", "context": "郵局ㄏㄨㄢ  ", "time": "2017/07/07 17:58:11", "event": "TYPE_VIEW_TEXT_CHANGED"}, {"category": "", "app": "Chrome", "id": "329", "context": "郵局換  ", "time": "2017/07/07 17:58:12", "event": "TYPE_VIEW_TEXT_CHANGED"}, {"category": "", "app": "Chrome", "id": "330", "context": "郵局換v  ", "time": "2017/07/07 17:58:14", "event": "TYPE_VIEW_TEXT_CHANGED"}, {"category": "", "app": "Chrome", "id": "331", "context": "郵局換vi  ", "time": "2017/07/07 17:58:15", "event": "TYPE_VIEW_TEXT_CHANGED"}, {"category": "", "app": "Chrome", "id": "332", "context": "郵局換vis  ", "time": "2017/07/07 17:58:15", "event": "TYPE_VIEW_TEXT_CHANGED"}, {"category": "", "app": "Chrome", "id": "333", "context": "郵局換visa  ", "time": "2017/07/07 17:58:15", "event": "TYPE_VIEW_TEXT_CHANGED"}, {"category": "", "app": "Chrome", "id": "334", "context": "郵局換visa - Google 搜尋 https://www.google.com.tw/search?q=郵局換visa&oq=郵局換visa&aqs=chrome..69i57j0l2.7839j0j4&client=ms-android-sonymobile&sourceid=chrome-mobile&ie=UTF-8", "time": "2017/07/07 17:58:17", "event": "TYPE_VIEW_SCROLLED"}, {"category": "", "app": "Chrome", "id": "335", "context": "郵政Visa金融卡 - 中華郵政全球資訊網 ", "time": "2017/07/07 17:58:19", "event": "TYPE_VIEW_FOCUSED"}, {"category": "", "app": "Chrome", "id": "336", "context": "郵政Visa金融卡 - 中華郵政全球資訊網  ", "time": "2017/07/07 17:58:19", "event": "TYPE_VIEW_CLICKED"}, {"category": "", "app": "Chrome", "id": "337", "context": "郵局換visa - Google 搜尋 https://www.post.gov.tw/post/internet/Visa/index.jsp?ID=1387695667603", "time": "2017/07/07 17:58:20", "event": "TYPE_VIEW_SCROLLED"}, {"category": "", "app": "Chrome", "id": "338", "context": "中華郵政全球資訊網 https://www.post.gov.tw", "time": "2017/07/07 17:58:25", "event": "TYPE_VIEW_SCROLLED"}, {"category": "", "app": "Chrome", "id": "339", "context": "常見問答 ", "time": "2017/07/07 17:59:30", "event": "TYPE_VIEW_FOCUSED"}, {"category": "", "app": "Chrome", "id": "340", "context": "常見問答  ", "time": "2017/07/07 17:59:30", "event": "TYPE_VIEW_CLICKED"}, {"category": "", "app": "Chrome", "id": "341", "context": "中華郵政全球資訊網 https://www.post.gov.tw/post/internet/Visa/index.jsp?ID=1003", "time": "2017/07/07 17:59:30", "event": "TYPE_VIEW_SCROLLED"}, {"category": "", "app": "Chrome", "id": "342", "context": "中華郵政全球資訊網 https://www.post.gov.tw", "time": "2017/07/07 17:59:33", "event": "TYPE_VIEW_SCROLLED"}, {"category": "", "app": "Chrome", "id": "343", "context": "已經持有郵政金融卡可以再申請VISA金融卡嗎？  ", "time": "2017/07/07 17:59:39", "event": "TYPE_VIEW_CLICKED"}, {"category": "", "app": "Chrome", "id": "344", "context": "中華郵政全球資訊網 https://www.post.gov.tw", "time": "2017/07/07 17:59:40", "event": "TYPE_VIEW_SCROLLED"}, {"category": "", "app": "Chrome", "id": "345", "context": "中華郵政全球資訊網 https://www.post.gov.tw/post/internet/Visa/index.jsp?ID=1387695667603", "time": "2017/07/07 17:59:57", "event": "TYPE_VIEW_SCROLLED"}, {"category": "", "app": "Chrome", "id": "346", "context": "郵局換visa - Google 搜尋 https://www.google.com.tw/search?q=郵局換visa&oq=郵局換visa&aqs=chrome..69i57j0l2.7839j0j4&client=ms-android-sonymobile&sourceid=chrome-mobile&ie=UTF-8", "time": "2017/07/07 17:59:59", "event": "TYPE_VIEW_SCROLLED"}, {"category": "", "app": "Chrome", "id": "347", "context": "新增分頁 ", "time": "2017/07/07 18:00:06", "event": "TYPE_VIEW_FOCUSED"}, {"category": "", "app": "com.sonyericsson.home", "id": "348", "context": "主畫面5之2  ", "time": "2017/07/07 18:00:22", "event": "TYPE_VIEW_CLICKED"}]